peertube_uploader/VERSION
peertube_uploader/__init__.py
peertube_uploader/main.py
peertube_uploader/requests.py
peertube_uploader/utils.py
peertube_uploader/actions/__init__.py
peertube_uploader/actions/append_dict_action.py
peertube_uploader/commands/__init__.py
peertube_uploader/commands/base_auth_command.py
peertube_uploader/commands/base_command.py
peertube_uploader/commands/get_access_token.py
peertube_uploader/commands/import_command.py
peertube_uploader/commands/types.py
peertube_uploader/commands/upload_base.py
peertube_uploader/commands/upload_video_command.py
peertube_uploader-1.0.0.dist-info/LICENSE
peertube_uploader-1.0.0.dist-info/METADATA
peertube_uploader-1.0.0.dist-info/WHEEL
peertube_uploader-1.0.0.dist-info/entry_points.txt
peertube_uploader-1.0.0.dist-info/top_level.txt
peertube_uploader-1.0.0.dist-info/RECORD
