Metadata-Version: 2.1
Name: peertube-uploader
Version: 1.0.0
Summary: A script to make uploading to peertube instances easier.
Home-page: https://gitlab.com/NamingThingsIsHard/media_tools/peertube-uploader
Author: LoveIsGrief
Author-email: loveisgrief@tuta.io
License: UNKNOWN
Project-URL: Bug Tracker, https://gitlab.com/NamingThingsIsHard/media_tools/peertube-uploader/issues
Platform: UNKNOWN
Classifier: Programming Language :: Python :: 3
Classifier: License :: OSI Approved :: GNU General Public License v3 (GPLv3)
Classifier: Operating System :: POSIX :: Linux
Requires-Dist: requests
Requires-Dist: cliff
